duneflow/__init__.py
duneflow/models/__init__.py
duneflow/models/_raw_table.py
duneflow/ops/__init__.py
duneflow/ops/curation/__init__.py
duneflow/ops/curation/_semantic_model.py
duneflow/ops/drepr/__init__.py
duneflow/ops/drepr/_convert_data.py
duneflow/ops/drepr/_make_drepr_model.py
duneflow/ops/drepr/_transformations.py
duneflow/ops/formatter/__init__.py
duneflow/ops/formatter/_to_column_based_table.py
duneflow/ops/matrix_to_relational.py
duneflow/ops/matrix_to_relational_v2.py
duneflow/ops/norm/__init__.py
duneflow/ops/norm/_norm_table.py
duneflow/ops/reader/__init__.py
duneflow/ops/reader/_get_html.py
duneflow/ops/reader/_scraper.py
duneflow/ops/reader/_table_file_reader.py
duneflow/ops/reader/_table_simple_select.py
duneflow/ops/select/__init__.py
duneflow/ops/select/_select_by_index.py
duneflow/ops/select/_table_range_select.py
duneflow/ops/select/_table_remove_column.py
duneflow/ops/split_repeated_block.py
duneflow/ops/writer/__init__.py
duneflow/ops/writer/_table.py
duneflow/ops/writer/_ttl.py
duneflow/typing.py
duneflow-1.0.2.dist-info/METADATA
duneflow-1.0.2.dist-info/WHEEL
duneflow-1.0.2.dist-info/RECORD
