Metadata-Version: 2.1
Name: duneflow
Version: 1.0.2
Summary: workflow for data analysis
License: MIT
Author: Binh Vu
Author-email: bvu687@gmail.com
Requires-Python: >=3.12,<4.0
Classifier: License :: OSI Approved :: MIT License
Classifier: Programming Language :: Python :: 3
Classifier: Programming Language :: Python :: 3.12
Classifier: Programming Language :: Python :: 3.13
Requires-Dist: lat-lon-parser (>=1.3.1,<2.0.0)
